sshlab/__init__.py
sshlab/sshlab.py
sshlab/sshlab_kill.py
sshlab/sshtensorboard.py
sshlab/utils.py
sshlab/version.py
sshlab-0.2.0.dist-info/LICENSE
sshlab-0.2.0.dist-info/METADATA
sshlab-0.2.0.dist-info/WHEEL
sshlab-0.2.0.dist-info/entry_points.txt
sshlab-0.2.0.dist-info/top_level.txt
sshlab-0.2.0.dist-info/RECORD
