Metadata-Version: 2.1
Name: sshlab
Version: 0.2.0
Summary: A tool for launching Jupyter Notebooks on remote servers using SSH
Home-page: https://github.com/vuillaut/sshlab
Author: Thomas Vuillaume
Author-email: thomas.vuillaume@lapp.in2p3.fr
Classifier: Development Status :: 3 - Alpha
Classifier: Intended Audience :: Developers
Classifier: License :: OSI Approved :: MIT License
Classifier: Operating System :: OS Independent
Classifier: Programming Language :: Python :: 3
Classifier: Programming Language :: Python :: 3.6
Classifier: Programming Language :: Python :: 3.7
Classifier: Programming Language :: Python :: 3.8
Classifier: Programming Language :: Python :: 3.9
License-File: LICENSE
Requires-Dist: PyYAML
Provides-Extra: doc
Requires-Dist: sphinx ; extra == 'doc'
Requires-Dist: furo ; extra == 'doc'
